typer_demo/__init__.py
typer_demo/main.py
typer_demo/utils/logger.py
typer_demo-0.2.2.dist-info/entry_points.txt
typer_demo-0.2.2.dist-info/LICENSE
typer_demo-0.2.2.dist-info/WHEEL
typer_demo-0.2.2.dist-info/METADATA
typer_demo-0.2.2.dist-info/RECORD
