Metadata-Version: 2.1
Name: typer-demo
Version: 0.2.2
Summary: typer cli demo
License: GPL v3
Author: Alex Pineda
Author-email: alehpineda@google.com
Requires-Python: >=3.9,<4.0
Classifier: License :: Other/Proprietary License
Classifier: Programming Language :: Python :: 3
Classifier: Programming Language :: Python :: 3.10
Classifier: Programming Language :: Python :: 3.9
Requires-Dist: typer (>=0.4.0,<0.5.0)
